spacy_lancedb_linker/__init__.py
spacy_lancedb_linker/kb.py
spacy_lancedb_linker/linker.py
spacy_lancedb_linker/types.py
spacy_lancedb_linker-0.1.2.dist-info/LICENSE
spacy_lancedb_linker-0.1.2.dist-info/METADATA
spacy_lancedb_linker-0.1.2.dist-info/WHEEL
spacy_lancedb_linker-0.1.2.dist-info/RECORD
