Metadata-Version: 2.1
Name: spacy-lancedb-linker
Version: 0.1.2
Summary: spaCy pipeline component for ANN Entity Linking using LanceDB
Home-page: https://guitton.co/
License: Apache-2.0
Keywords: spacy,spacy-pipeline,entity-linking,ann,lancedb
Author: Louis Guitton
Author-email: admin@guitton.co
Requires-Python: >=3.12,<4.0
Classifier: Development Status :: 3 - Alpha
Classifier: Intended Audience :: Developers
Classifier: License :: OSI Approved :: Apache Software License
Classifier: Programming Language :: Python :: 3
Classifier: Programming Language :: Python :: 3.12
Classifier: Topic :: Scientific/Engineering :: Artificial Intelligence
Classifier: Topic :: Software Development :: Libraries :: Python Modules
Requires-Dist: lancedb (>=0.13.0,<0.14.0)
Requires-Dist: pydantic (>=2.9.2,<3.0.0)
Requires-Dist: sentence-transformers (>=3.1.1,<4.0.0)
Requires-Dist: spacy (>=3.7.6,<4.0.0)
Requires-Dist: tantivy (>=0.22.0,<0.23.0)
Project-URL: Documentation, https://guitton.co/
Project-URL: Repository, https://github.com/louisguitton/spacy-lancedb-linker
